<?xml version="1.0" encoding="ISO-8859-1"?>
<gateway compatibility="1" xmlns:xsi="http://www.w3.org/2001/XMLSchema-instance" xsi:noNamespaceSchemaLocation="http://schema.itrsgroup.com/GA3.0.6-130308/gateway.xsd">
	<includes>
		<priority>1</priority>
		<include>
			<priority>2</priority>
			<required>true</required>
			<location>config/netprobes</location>
		</include>
		<include>
			<priority>3</priority>
			<required>true</required>
			<location>config/managed_entities</location>
		</include>
		<includeGroup name="BASE COMMON">
			<include>
				<priority>14</priority>
				<required>true</required>
				<location>../../gateway_config/shared/ett/gateway_monitor_stats</location>
			</include>
			<include>
				<priority>23</priority>
				<required>true</required>
				<location>../../gateway_config/shared/ett/active times</location>
			</include>
			<include>
				<priority>27</priority>
				<required>true</required>
				<location>../../gateway_config/shared/ett/commands</location>
			</include>
			<include>
				<priority>30</priority>
				<required>true</required>
				<location>../../gateway_config/shared/ett/hardware</location>
			</include>
			<include>
				<priority>90</priority>
				<required>true</required>
				<location>../../gateway_config/shared/ett/base_static_variables</location>
			</include>
			<include>
				<priority>92</priority>
				<required>true</required>
				<location>../../gateway_config/shared/ett/knowledge_base</location>
			</include>
			<include>
				<priority>93</priority>
				<required>true</required>
				<location>../../gateway_config/shared/ett/database</location>
			</include>
			<include>
				<priority>22</priority>
				<required>true</required>
				<location>../../gateway_config/shared/ett/all_samplers</location>
			</include>
		</includeGroup>
		<includeGroup name="ETT COMMON">
			<include>
				<priority>7</priority>
				<required>true</required>
				<location>../../gateway_config/shared/ett/ett_rules</location>
			</include>
			<include>
				<priority>32</priority>
				<required>true</required>
				<location>../../gateway_config/shared/ett/ett_types</location>
			</include>
			<include>
				<priority>28</priority>
				<required>true</required>
				<location>../../gateway_config/shared/ett/ett_samplers</location>
			</include>
		</includeGroup>
	</includes>
	<operatingEnvironment>
		<!--The gateway name must be set, the listen port should be set-->
		<gatewayName>ETT US</gatewayName>
		<listenPort>8083</listenPort>
	</operatingEnvironment>
</gateway>